pest/__init__.py
pest/core/__init__.py
pest/core/application.py
pest/core/common/__init__.py
pest/core/controller.py
pest/core/handler.py
pest/core/module.py
pest/core/types/fastapi_params.py
pest/core/types/status.py
pest/decorators/_common.py
pest/decorators/controller.py
pest/decorators/dicts/controller_dict.py
pest/decorators/dicts/handler_dict.py
pest/decorators/dicts/module_dict.py
pest/decorators/guard.py
pest/decorators/handler.py
pest/decorators/module.py
pest/di/__init__.py
pest/di/injection.py
pest/exceptions/__init__.py
pest/exceptions/base/pest.py
pest/exceptions/handle.py
pest/exceptions/http/http.py
pest/exceptions/http/status.py
pest/factory/__init__.py
pest/factory/app_creator.py
pest/factory/openapi.py
pest/factory/post_app.py
pest/factory/pre_app.py
pest/logging/__init__.py
pest/logging/loguru/__init__.py
pest/logging/loguru/loguru.py
pest/metadata/__init__.py
pest/metadata/meta.py
pest/metadata/types/_meta.py
pest/metadata/types/controller_meta.py
pest/metadata/types/handler_meta.py
pest/metadata/types/injectable_meta.py
pest/metadata/types/module_meta.py
pest/middleware/base.py
pest/middleware/di.py
pest/middleware/types.py
pest/schedule/__init__.py
pest/schedule/decorators/cron.py
pest/schedule/decorators/types/cron_meta.py
pest/schedule/decorators/types/dicts/cron_dict.py
pest/schedule/module/schedule_module.py
pest/schedule/module/services/scheduler_explorer.py
pest/utils/colorize.py
pest/utils/decorators.py
pest/utils/fastapi/router.py
pest/utils/functions.py
pest/utils/module.py
pest/utils/protocols.py
pest_py-0.5.5.dist-info/METADATA
pest_py-0.5.5.dist-info/WHEEL
pest_py-0.5.5.dist-info/licenses/LICENSE
pest_py-0.5.5.dist-info/RECORD
