Metadata-Version: 2.4
Name: pest-py
Version: 0.5.5
Summary: 🐀 ⇝ pest › fastapi + rodi + mvc | python library for building scalable modular API's. Inspired by NestJS.
License: MIT
License-File: LICENSE
Keywords: pest,nestjs,nest,api,rest,restful,mvc,web,webapp,di,dependency injection,rodi,fastapi
Author: Lucas Colombo
Author-email: lucas@lucode.dev
Requires-Python: >=3.11,<4.0
Classifier: Intended Audience :: Information Technology
Classifier: Intended Audience :: System Administrators
Classifier: Operating System :: OS Independent
Classifier: Programming Language :: Python :: 3
Classifier: Programming Language :: Python
Classifier: Topic :: Internet
Classifier: Topic :: Software Development :: Libraries :: Application Frameworks
Classifier: Topic :: Software Development :: Libraries :: Python Modules
Classifier: Topic :: Software Development :: Libraries
Classifier: Topic :: Software Development
Classifier: Typing :: Typed
Classifier: Development Status :: 4 - Beta
Classifier: Environment :: Web Environment
Classifier: Framework :: AsyncIO
Classifier: Framework :: FastAPI
Classifier: Framework :: Pydantic
Classifier: Framework :: Pydantic :: 1
Classifier: Intended Audience :: Developers
Classifier: License :: OSI Approved :: MIT License
Classifier: Topic :: Internet :: WWW/HTTP :: HTTP Servers
Classifier: Topic :: Internet :: WWW/HTTP
Provides-Extra: cron
Provides-Extra: logs
Requires-Dist: croniter (>=6.0.0,<7.0.0) ; extra == "cron"
Requires-Dist: dacite (>=1.9.2)
Requires-Dist: dij (>=0.0.4,<0.1.0)
Requires-Dist: fastapi (>=0.121.0,<0.122.0)
Requires-Dist: loguru (>=0.7.0,<0.8.0) ; extra == "logs"
Requires-Dist: pydantic (>=1.7.4,!=1.8,!=1.8.1,!=2.0.0,!=2.0.1,!=2.1.0,<3.0.0)
Requires-Dist: typing-extensions (>=4.8.0)
Project-URL: Bug Tracker, https://github.com/lucas-labs/pest/issues
Project-URL: Documentation, https://pest.lucode.dev/docs
Project-URL: Homepage, https://pest.lucode.dev
Project-URL: Repository, https://github.com/lucas-labs/pest
